Metadata-Version: 2.1
Name: odoo-addon-l10n_es_payment_order_confirming_sabadell
Version: 18.0.1.0.1
Requires-Python: >=3.10
Requires-Dist: odoo-addon-account_payment_order==18.0.*
Requires-Dist: odoo==18.0.*
Summary: =?utf-8?q?Exportaci=C3=B3n_de_fichero_bancario_Confirming_para_Banco_Sabadell?=
Home-page: https://github.com/OCA/l10n-spain
License: AGPL-3
Author: Soluntec, Odoo Community Association (OCA), Tecnativa
Author-email: support@odoo-community.org
Classifier: Programming Language :: Python
Classifier: Framework :: Odoo
Classifier: Framework :: Odoo :: 18.0
Classifier: License :: OSI Approved :: GNU Affero General Public License v3
